{
  "interests": [
    {
      "label": "Javascript",
      "image": {
        "src": "../../images/java-script.png",
        "alt": ""
      }
    },
    {
      "label": "Ruby",
      "image": {
        "src": "../../images/ruby.png",
        "alt": ""
      }
    },
    {
      "label": "API development",
      "image": {
        "src": "../../images/api.png",
        "alt": ""
      }
    },
    {
      "label": "Data Structures and Algorithms",
      "image": {
        "src": "../../images/structure.png",
        "alt": ""
      }
    },
    {
      "label": "ReactJS",
      "image": {
        "src": "../../images/react.png",
        "alt": ""
      }
    },
    {
      "label": "PWA (Offline Support)",
      "image": {
        "src": "../../images/mobile-phone.png",
        "alt": ""
      }
    },
    {
      "label": "",
      "image": {
        "src": "../../images/gatsby.png",
        "alt": ""
      }
    },
    {
      "label": "",
      "image": {
        "src": "../../images/high-voltage.png",
        "alt": ""
      }
    }
  ],
  "button": {
    "visible": true,
    "label": "+ Load More",
    "initiallyShownInterests": 5
  }
}
